CheckHttp.py
CheckHttpStatusCode.py
checkhttpstatuscode-1.0.3.dist-info/METADATA
checkhttpstatuscode-1.0.3.dist-info/RECORD
checkhttpstatuscode-1.0.3.dist-info/WHEEL
checkhttpstatuscode-1.0.3.dist-info/entry_points.txt
checkhttpstatuscode-1.0.3.dist-info/top_level.txt
