Metadata-Version: 2.1
Name: checkhttpstatuscode
Version: 1.0.3
Summary: Check the status codes of http servers
Home-page: https://gitlab.com/gregoryjordanm/checkhttpstatus
Author: Jordan Gregory
Author-email: gregory.jordan.m@gmail.com
License: MIT
Platform: UNKNOWN
Requires-Dist: Click
Requires-Dist: requests
